{
  "admin" : {
    "nom" : "administration",
    "id" : "admin",
    "icone" : "",
    "niveau" : "niv_1",
    "hasSousmenu" : true
  },
  "users" : {
    "nom" : "Utilisateurs",
    "route" : "admin.utilisateurs",
    "icone" : "infos_perso.svg",
    "niveau" : "niv_2",
    "parent" : "admin",
    "hasSousmenu" : false
  },
  "notes" : {
    "nom" : "Notes",
    "route" : "admin.notes",
    "icone" : "insulte.svg",
    "niveau" : "niv_2",
    "parent" : "admin",
    "hasSousmenu" : false
  },
  "indicateurs" : {
    "nom" : "gestion des indicateurs",
    "id" : "indicateurs",
    "icone" : "",
    "niveau" : "niv_1",
    "hasSousmenu" : true
  },
  "chiffres" : {
    "nom" : "Chiffres",
    "route" : "chiffre.index",
    "icone" : "saisie/chiffres.svg",
    "niveau" : "niv_2",
    "parent" : "indicateurs",
    "hasSousmenu" : false
  },
  "alertes" : {
    "nom" : "Alertes",
    "id" : "alertes",
    "icone" : "saisie/alertes.svg",
    "niveau" : "niv_2",
    "parent" : "indicateurs",
    "hasSousmenu" : true
  },
  "parafermes" : {
    "nom" : "Paramètres des exploitations",
    "id" : "parafermes",
    "route" : "paraferme.index",
    "icone" : "categories/logement.svg",
    "niveau" : "niv_2",
    "parent" : "indicateurs",
    "hasSousmenu" : false
  },
  "vl" : {
    "nom" : "Vaches laitières",
    "route" : "alerte.indexParEspece",
    "id" : "Vaches laitières",
    "niveau" : "niv_3",
    "parent" : "alertes",
    "icone" : "especes/VL.svg"
  },
  "va" : {
    "nom" : "Vaches allaitantes",
    "route" : "alerte.indexParEspece",
    "id" : "Vaches allaitantes",
    "niveau" : "niv_3",
    "parent" : "alertes",
    "icone" : "especes/VA.svg"
  },
  "oa" : {
    "nom" : "Brebis allaitantes",
    "route" : "alerte.indexParEspece",
    "id" : "Brebis allaitantes",
    "niveau" : "niv_3",
    "parent" : "alertes",
    "icone" : "especes/OA.svg"
  },
  "cp" : {
    "nom" : "Chèvres laitières",
    "route" : "alerte.indexParEspece",
    "id" : "Chèvres laitières",
    "niveau" : "niv_3",
    "parent" : "alertes",
    "icone" : "especes/CP.svg"
  },
  "ol" : {
    "nom" : "Brebis laitières",
    "route" : "alerte.indexParEspece",
    "id" : "Brebis laitières",
    "niveau" : "niv_3",
    "parent" : "alertes",
    "icone" : "especes/OL.svg"
  }
}
